<annotation>
	<folder>images</folder>
	<filename>1019200_5.PNG</filename>
	<path>C:\Users\murtaza.nazir\OneDrive - Subex Limited\Downloads\Table detection\datasheets\final_data\images\1019200_5.PNG</path>
	<source>
		<database>Unknown</database>
	</source>
	<size>
		<width>4675</width>
		<height>6050</height>
		<depth>3</depth>
	</size>
	<segmented>0</segmented>
	<object>
		<name>Table</name>
		<pose>Unspecified</pose>
		<truncated>0</truncated>
		<difficult>0</difficult>
		<bndbox>
			<xmin>393</xmin>
			<ymin>1170</ymin>
			<xmax>4186</xmax>
			<ymax>1974</ymax>
		</bndbox>
	</object>
	<object>
		<name>Table</name>
		<pose>Unspecified</pose>
		<truncated>0</truncated>
		<difficult>0</difficult>
		<bndbox>
			<xmin>2374</xmin>
			<ymin>2173</ymin>
			<xmax>4185</xmax>
			<ymax>2775</ymax>
		</bndbox>
	</object>
	<object>
		<name>Table</name>
		<pose>Unspecified</pose>
		<truncated>0</truncated>
		<difficult>0</difficult>
		<bndbox>
			<xmin>2373</xmin>
			<ymin>3518</ymin>
			<xmax>4186</xmax>
			<ymax>4904</ymax>
		</bndbox>
	</object>
</annotation>
