<annotation>
	<folder>images</folder>
	<filename>1589600_3.PNG</filename>
	<path>C:\Users\murtaza.nazir\OneDrive - Subex Limited\Downloads\Table detection\datasheets\final_data\images\1589600_3.PNG</path>
	<source>
		<database>Unknown</database>
	</source>
	<size>
		<width>4653</width>
		<height>6058</height>
		<depth>1</depth>
	</size>
	<segmented>0</segmented>
	<object>
		<name>Table</name>
		<pose>Unspecified</pose>
		<truncated>0</truncated>
		<difficult>0</difficult>
		<bndbox>
			<xmin>1322</xmin>
			<ymin>2361</ymin>
			<xmax>3377</xmax>
			<ymax>3874</ymax>
		</bndbox>
	</object>
</annotation>
