<annotation>
	<folder>images</folder>
	<filename>1640000_0.PNG</filename>
	<path>C:\Users\murtaza.nazir\OneDrive - Subex Limited\Downloads\Table detection\datasheets\final_data\images\1640000_0.PNG</path>
	<source>
		<database>Unknown</database>
	</source>
	<size>
		<width>4675</width>
		<height>6050</height>
		<depth>3</depth>
	</size>
	<segmented>0</segmented>
	<object>
		<name>Table</name>
		<pose>Unspecified</pose>
		<truncated>0</truncated>
		<difficult>0</difficult>
		<bndbox>
			<xmin>366</xmin>
			<ymin>2627</ymin>
			<xmax>2200</xmax>
			<ymax>3054</ymax>
		</bndbox>
	</object>
</annotation>
