<annotation>
	<folder>images</folder>
	<filename>1663200_9.PNG</filename>
	<path>C:\Users\murtaza.nazir\OneDrive - Subex Limited\Downloads\Table detection\datasheets\final_data\images\1663200_9.PNG</path>
	<source>
		<database>Unknown</database>
	</source>
	<size>
		<width>4546</width>
		<height>6432</height>
		<depth>1</depth>
	</size>
	<segmented>0</segmented>
	<object>
		<name>Table</name>
		<pose>Unspecified</pose>
		<truncated>0</truncated>
		<difficult>0</difficult>
		<bndbox>
			<xmin>1030</xmin>
			<ymin>1891</ymin>
			<xmax>2944</xmax>
			<ymax>1984</ymax>
		</bndbox>
	</object>
	<object>
		<name>Table</name>
		<pose>Unspecified</pose>
		<truncated>0</truncated>
		<difficult>0</difficult>
		<bndbox>
			<xmin>1030</xmin>
			<ymin>2101</ymin>
			<xmax>2944</xmax>
			<ymax>2196</ymax>
		</bndbox>
	</object>
	<object>
		<name>Table</name>
		<pose>Unspecified</pose>
		<truncated>0</truncated>
		<difficult>0</difficult>
		<bndbox>
			<xmin>2394</xmin>
			<ymin>2422</ymin>
			<xmax>2943</xmax>
			<ymax>2695</ymax>
		</bndbox>
	</object>
	<object>
		<name>Table</name>
		<pose>Unspecified</pose>
		<truncated>0</truncated>
		<difficult>0</difficult>
		<bndbox>
			<xmin>1030</xmin>
			<ymin>2421</ymin>
			<xmax>2319</xmax>
			<ymax>2817</ymax>
		</bndbox>
	</object>
	<object>
		<name>Table</name>
		<pose>Unspecified</pose>
		<truncated>0</truncated>
		<difficult>0</difficult>
		<bndbox>
			<xmin>2384</xmin>
			<ymin>3120</ymin>
			<xmax>3461</xmax>
			<ymax>4030</ymax>
		</bndbox>
	</object>
	<object>
		<name>Table</name>
		<pose>Unspecified</pose>
		<truncated>0</truncated>
		<difficult>0</difficult>
		<bndbox>
			<xmin>1028</xmin>
			<ymin>3121</ymin>
			<xmax>1775</xmax>
			<ymax>3938</ymax>
		</bndbox>
	</object>
</annotation>
