<annotation>
	<folder>images</folder>
	<filename>1692800_3.PNG</filename>
	<path>C:\Users\murtaza.nazir\OneDrive - Subex Limited\Downloads\Table detection\datasheets\final_data\images\1692800_3.PNG</path>
	<source>
		<database>Unknown</database>
	</source>
	<size>
		<width>4546</width>
		<height>6432</height>
		<depth>1</depth>
	</size>
	<segmented>0</segmented>
	<object>
		<name>Table</name>
		<pose>Unspecified</pose>
		<truncated>0</truncated>
		<difficult>0</difficult>
		<bndbox>
			<xmin>404</xmin>
			<ymin>628</ymin>
			<xmax>4143</xmax>
			<ymax>3201</ymax>
		</bndbox>
	</object>
</annotation>
