<annotation>
	<folder>images</folder>
	<filename>1859200_0.PNG</filename>
	<path>C:\Users\murtaza.nazir\OneDrive - Subex Limited\Downloads\Table detection\datasheets\final_data\images\1859200_0.PNG</path>
	<source>
		<database>Unknown</database>
	</source>
	<size>
		<width>3713</width>
		<height>4897</height>
		<depth>1</depth>
	</size>
	<segmented>0</segmented>
	<object>
		<name>Table</name>
		<pose>Unspecified</pose>
		<truncated>0</truncated>
		<difficult>0</difficult>
		<bndbox>
			<xmin>123</xmin>
			<ymin>1690</ymin>
			<xmax>2351</xmax>
			<ymax>4747</ymax>
		</bndbox>
	</object>
</annotation>
