<annotation>
	<folder>images</folder>
	<filename>1940000_3.PNG</filename>
	<path>C:\Users\murtaza.nazir\OneDrive - Subex Limited\Downloads\Table detection\datasheets\final_data\images\1940000_3.PNG</path>
	<source>
		<database>Unknown</database>
	</source>
	<size>
		<width>4675</width>
		<height>6050</height>
		<depth>1</depth>
	</size>
	<segmented>0</segmented>
	<object>
		<name>Table</name>
		<pose>Unspecified</pose>
		<truncated>0</truncated>
		<difficult>0</difficult>
		<bndbox>
			<xmin>548</xmin>
			<ymin>1200</ymin>
			<xmax>2277</xmax>
			<ymax>1898</ymax>
		</bndbox>
	</object>
	<object>
		<name>Table</name>
		<pose>Unspecified</pose>
		<truncated>0</truncated>
		<difficult>0</difficult>
		<bndbox>
			<xmin>533</xmin>
			<ymin>2239</ymin>
			<xmax>3389</xmax>
			<ymax>2884</ymax>
		</bndbox>
	</object>
	<object>
		<name>Table</name>
		<pose>Unspecified</pose>
		<truncated>0</truncated>
		<difficult>0</difficult>
		<bndbox>
			<xmin>527</xmin>
			<ymin>3174</ymin>
			<xmax>2249</xmax>
			<ymax>3474</ymax>
		</bndbox>
	</object>
</annotation>
