<annotation>
	<folder>images</folder>
	<filename>3124800_1.PNG</filename>
	<path>C:\Users\murtaza.nazir\OneDrive - Subex Limited\Downloads\Table detection\datasheets\final_data\images\3124800_1.PNG</path>
	<source>
		<database>Unknown</database>
	</source>
	<size>
		<width>4675</width>
		<height>6050</height>
		<depth>3</depth>
	</size>
	<segmented>0</segmented>
	<object>
		<name>Table</name>
		<pose>Unspecified</pose>
		<truncated>0</truncated>
		<difficult>0</difficult>
		<bndbox>
			<xmin>273</xmin>
			<ymin>1167</ymin>
			<xmax>4387</xmax>
			<ymax>1856</ymax>
		</bndbox>
	</object>
	<object>
		<name>Table</name>
		<pose>Unspecified</pose>
		<truncated>0</truncated>
		<difficult>0</difficult>
		<bndbox>
			<xmin>273</xmin>
			<ymin>2040</ymin>
			<xmax>4407</xmax>
			<ymax>2925</ymax>
		</bndbox>
	</object>
	<object>
		<name>Table</name>
		<pose>Unspecified</pose>
		<truncated>0</truncated>
		<difficult>0</difficult>
		<bndbox>
			<xmin>273</xmin>
			<ymin>3109</ymin>
			<xmax>4399</xmax>
			<ymax>4900</ymax>
		</bndbox>
	</object>
</annotation>
