<annotation>
	<folder>images</folder>
	<filename>3147200_15.PNG</filename>
	<path>C:\Users\murtaza.nazir\OneDrive - Subex Limited\Downloads\Table detection\datasheets\final_data\images\3147200_15.PNG</path>
	<source>
		<database>Unknown</database>
	</source>
	<size>
		<width>4653</width>
		<height>6058</height>
		<depth>3</depth>
	</size>
	<segmented>0</segmented>
	<object>
		<name>Table</name>
		<pose>Unspecified</pose>
		<truncated>0</truncated>
		<difficult>0</difficult>
		<bndbox>
			<xmin>433</xmin>
			<ymin>4498</ymin>
			<xmax>1775</xmax>
			<ymax>4820</ymax>
		</bndbox>
	</object>
	<object>
		<name>Table</name>
		<pose>Unspecified</pose>
		<truncated>0</truncated>
		<difficult>0</difficult>
		<bndbox>
			<xmin>2774</xmin>
			<ymin>4496</ymin>
			<xmax>4113</xmax>
			<ymax>4820</ymax>
		</bndbox>
	</object>
	<object>
		<name>Table</name>
		<pose>Unspecified</pose>
		<truncated>0</truncated>
		<difficult>0</difficult>
		<bndbox>
			<xmin>2375</xmin>
			<ymin>3954</ymin>
			<xmax>4105</xmax>
			<ymax>4276</ymax>
		</bndbox>
	</object>
</annotation>
