<annotation>
	<folder>images</folder>
	<filename>554400_1.PNG</filename>
	<path>C:\Users\murtaza.nazir\OneDrive - Subex Limited\Downloads\Table detection\datasheets\final_data\images\554400_1.PNG</path>
	<source>
		<database>Unknown</database>
	</source>
	<size>
		<width>4675</width>
		<height>6050</height>
		<depth>1</depth>
	</size>
	<segmented>0</segmented>
	<object>
		<name>Table</name>
		<pose>Unspecified</pose>
		<truncated>0</truncated>
		<difficult>0</difficult>
		<bndbox>
			<xmin>275</xmin>
			<ymin>627</ymin>
			<xmax>1925</xmax>
			<ymax>1389</ymax>
		</bndbox>
	</object>
	<object>
		<name>Table</name>
		<pose>Unspecified</pose>
		<truncated>0</truncated>
		<difficult>0</difficult>
		<bndbox>
			<xmin>2475</xmin>
			<ymin>628</ymin>
			<xmax>4298</xmax>
			<ymax>1500</ymax>
		</bndbox>
	</object>
	<object>
		<name>Table</name>
		<pose>Unspecified</pose>
		<truncated>0</truncated>
		<difficult>0</difficult>
		<bndbox>
			<xmin>2434</xmin>
			<ymin>1831</ymin>
			<xmax>4304</xmax>
			<ymax>2171</ymax>
		</bndbox>
	</object>
	<object>
		<name>Table</name>
		<pose>Unspecified</pose>
		<truncated>0</truncated>
		<difficult>0</difficult>
		<bndbox>
			<xmin>2474</xmin>
			<ymin>2521</ymin>
			<xmax>4261</xmax>
			<ymax>3311</ymax>
		</bndbox>
	</object>
</annotation>
