<annotation>
	<folder>images</folder>
	<filename>datasheet(12)_23.PNG</filename>
	<path>C:\Users\murtaza.nazir\OneDrive - Subex Limited\Downloads\Table detection\datasheets\final_data\images\datasheet(12)_23.PNG</path>
	<source>
		<database>Unknown</database>
	</source>
	<size>
		<width>4546</width>
		<height>6432</height>
		<depth>1</depth>
	</size>
	<segmented>0</segmented>
	<object>
		<name>Table</name>
		<pose>Unspecified</pose>
		<truncated>0</truncated>
		<difficult>0</difficult>
		<bndbox>
			<xmin>534</xmin>
			<ymin>2225</ymin>
			<xmax>2196</xmax>
			<ymax>3863</ymax>
		</bndbox>
	</object>
	<object>
		<name>Table</name>
		<pose>Unspecified</pose>
		<truncated>0</truncated>
		<difficult>0</difficult>
		<bndbox>
			<xmin>2443</xmin>
			<ymin>2225</ymin>
			<xmax>4099</xmax>
			<ymax>3864</ymax>
		</bndbox>
	</object>
	<object>
		<name>Table</name>
		<pose>Unspecified</pose>
		<truncated>0</truncated>
		<difficult>0</difficult>
		<bndbox>
			<xmin>531</xmin>
			<ymin>4056</ymin>
			<xmax>2196</xmax>
			<ymax>5819</ymax>
		</bndbox>
	</object>
	<object>
		<name>Table</name>
		<pose>Unspecified</pose>
		<truncated>0</truncated>
		<difficult>0</difficult>
		<bndbox>
			<xmin>2441</xmin>
			<ymin>4054</ymin>
			<xmax>4101</xmax>
			<ymax>5817</ymax>
		</bndbox>
	</object>
</annotation>
