<annotation>
	<folder>reports_images</folder>
	<filename>LSE_III_2009_39.png</filename>
	<path>C:\Users\murtaza.nazir\OneDrive - Subex Limited\Downloads\Table detection\datasheets\Table detection dataset\reports_images\LSE_III_2009_39.png</path>
	<source>
		<database>Unknown</database>
	</source>
	<size>
		<width>1812</width>
		<height>2339</height>
		<depth>3</depth>
	</size>
	<segmented>0</segmented>
	<object>
		<name>Table</name>
		<pose>Unspecified</pose>
		<truncated>0</truncated>
		<difficult>0</difficult>
		<bndbox>
			<xmin>117</xmin>
			<ymin>499</ymin>
			<xmax>1648</xmax>
			<ymax>1413</ymax>
		</bndbox>
	</object>
	<object>
		<name>Table</name>
		<pose>Unspecified</pose>
		<truncated>0</truncated>
		<difficult>0</difficult>
		<bndbox>
			<xmin>903</xmin>
			<ymin>1515</ymin>
			<xmax>1652</xmax>
			<ymax>1762</ymax>
		</bndbox>
	</object>
</annotation>
